<annotation>
	<folder>train</folder>
	<filename>train_45.jpg</filename>
	<path>/Volumes/192.168.1.120/nick/Documents/Citrus Leafminer/train/train_45.jpg</path>
	<source>
		<database>Unknown</database>
	</source>
	<size>
		<width>4912</width>
		<height>3264</height>
		<depth>3</depth>
	</size>
	<segmented>0</segmented>
	<object>
		<name>damage</name>
		<pose>Unspecified</pose>
		<truncated>0</truncated>
		<difficult>0</difficult>
		<bndbox>
			<xmin>2824</xmin>
			<ymin>618</ymin>
			<xmax>3340</xmax>
			<ymax>2114</ymax>
		</bndbox>
	</object>
	<object>
		<name>damage</name>
		<pose>Unspecified</pose>
		<truncated>0</truncated>
		<difficult>0</difficult>
		<bndbox>
			<xmin>2984</xmin>
			<ymin>1870</ymin>
			<xmax>3852</xmax>
			<ymax>3110</ymax>
		</bndbox>
	</object>
	<object>
		<name>damage</name>
		<pose>Unspecified</pose>
		<truncated>0</truncated>
		<difficult>0</difficult>
		<bndbox>
			<xmin>2084</xmin>
			<ymin>1850</ymin>
			<xmax>2436</xmax>
			<ymax>2394</ymax>
		</bndbox>
	</object>
	<object>
		<name>damage</name>
		<pose>Unspecified</pose>
		<truncated>0</truncated>
		<difficult>0</difficult>
		<bndbox>
			<xmin>2168</xmin>
			<ymin>1158</ymin>
			<xmax>2556</xmax>
			<ymax>1834</ymax>
		</bndbox>
	</object>
	<object>
		<name>damage</name>
		<pose>Unspecified</pose>
		<truncated>0</truncated>
		<difficult>0</difficult>
		<bndbox>
			<xmin>1832</xmin>
			<ymin>1374</ymin>
			<xmax>2196</xmax>
			<ymax>1610</ymax>
		</bndbox>
	</object>
</annotation>
